student/__init__.py
student/admin.py
student/app_settings.py
student/apps.py
student/auth_hooks.py
student/models.py
student/signals.py
student/tasks.py
student/urls.py
student/views.py
student/migrations/0001_initial.py
student/migrations/__init__.py
student/templates/student/base.html
student/templates/student/index.html
student/tests/__init__.py
student/tests/test_tasks.py
aa_student-0.3.0.dist-info/LICENSE
aa_student-0.3.0.dist-info/WHEEL
aa_student-0.3.0.dist-info/METADATA
aa_student-0.3.0.dist-info/RECORD
